videoslice/__init__.py
videoslice/download.py
videoslice/program_runner.py
videoslice/runner.py
videoslice/slice.py
videoslice-0.1.0.dist-info/METADATA
videoslice-0.1.0.dist-info/WHEEL
videoslice-0.1.0.dist-info/entry_points.txt
videoslice-0.1.0.dist-info/licenses/LICENSE
videoslice-0.1.0.dist-info/RECORD
