Metadata-Version: 2.4
Name: videoslice
Version: 0.1.0
Summary: A tool to slice YouTube videos into smaller segments
Author-email: Meek Msaki <meek10x+videoslice@gmail.com>
License-Expression: MIT
License-File: LICENSE
Keywords: ffmpeg,slicing,tool,video,youtube
Requires-Python: >=3.10
